timescale_vector/__init__.py
timescale_vector/_modidx.py
timescale_vector/client.py
timescale_vector/pgvectorizer.py
timescale_vector-0.0.7.dist-info/LICENSE
timescale_vector-0.0.7.dist-info/METADATA
timescale_vector-0.0.7.dist-info/NOTICE
timescale_vector-0.0.7.dist-info/WHEEL
timescale_vector-0.0.7.dist-info/entry_points.txt
timescale_vector-0.0.7.dist-info/top_level.txt
timescale_vector-0.0.7.dist-info/RECORD
