Metadata-Version: 2.1
Name: timescale-vector
Version: 0.0.7
Summary: Python library for storing vector data in Postgres
Home-page: https://github.com/timescale/python-vector
Author: Matvey Arye
Author-email: mat@timescale.com
License: Apache Software License 2.0
Keywords: nbdev jupyter notebook python
Classifier: Development Status :: 4 - Beta
Classifier: Intended Audience :: Developers
Classifier: Natural Language :: English
Classifier: Programming Language :: Python :: 3.7
Classifier: Programming Language :: Python :: 3.8
Classifier: Programming Language :: Python :: 3.9
Classifier: Programming Language :: Python :: 3.10
Classifier: License :: OSI Approved :: Apache Software License
Requires-Python: >=3.7
License-File: LICENSE
License-File: NOTICE
Requires-Dist: asyncpg
Requires-Dist: psycopg2
Requires-Dist: pgvector
Provides-Extra: dev
Requires-Dist: python-dotenv ; extra == 'dev'
Requires-Dist: langchain ; extra == 'dev'
Requires-Dist: langchain-openai ; extra == 'dev'
Requires-Dist: langchain-community ; extra == 'dev'
